plyball/__init__.py
plyball/baseballreference/__init__.py
plyball/baseballreference/baseballreference.py
plyball/fangraphs/__init__.py
plyball/fangraphs/fangraphs.py
plyball/lahman/__init__.py
plyball/lahman/lahman.py
plyball/mlb/__init__.py
plyball/mlb/examples/box_score.json
plyball/mlb/models/__init__.py
plyball/mlb/models/box_score.py
plyball/ottoneu/__init__.py
plyball/ottoneu/ottoneu.py
plyball/pipeline/__init__.py
plyball/pipeline/evaluation.py
plyball/player_id_lookup.py
plyball/player_map.py
plyball/retrosheet/__init__.py
plyball/retrosheet/retrosheet.py
plyball/statcast/__init__.py
plyball/statcast/statcast.py
plyball/utils.py
plyball-2.6.15.dist-info/LICENSE.txt
plyball-2.6.15.dist-info/METADATA
plyball-2.6.15.dist-info/WHEEL
plyball-2.6.15.dist-info/RECORD
